{
  "raw_metadata_rows": 162,
  "existing_metadata_rows": 0,
  "distinct_physical_files": 0,
  "raw_rows_by_file_group": {
    "PDF": 120,
    "VID": 28,
    "IMG": 14
  },
  "distinct_files_by_file_group": {},
  "distinct_files_by_extension": {},
  "raw_rows_by_agency": {
    "Department of War": 82,
    "FBI": 56,
    "NASA": 16,
    "Department of State": 8
  },
  "distinct_files_by_agency": {},
  "duplicate_output_paths": {},
  "total_size_mib": 0.0,
  "size_mib_by_file_group": {},
  "pdf_pages": {
    "known_count": 0,
    "total_pages": 0,
    "max_pages": 0
  },
  "video_duration_sec": {
    "known_count": 0,
    "total_sec": 0.0,
    "max_sec": NaN
  }
}